bandai/__init__.py
bandai/main.py
bandai/utils.py
bandai/bandits/__init__.py
bandai/bandits/disjoint_lin_ucb.py
bandai/bandits/joint_lin_ucb.py
bandai/bandits/protocols.py
bandai_lib-0.0.6.dist-info/licenses/LICENSE
bandai_lib-0.0.6.dist-info/METADATA
bandai_lib-0.0.6.dist-info/WHEEL
bandai_lib-0.0.6.dist-info/entry_points.txt
bandai_lib-0.0.6.dist-info/top_level.txt
bandai_lib-0.0.6.dist-info/RECORD
