Metadata-Version: 2.4
Name: bandai-lib
Version: 0.0.6
Summary: 🕹 bandai: bandits for ai
Author-email: Arkadiy Vladimirov <ark.vladimirov@outlook.com>
License: MIT
Requires-Python: >=3.10
License-File: LICENSE
Requires-Dist: jaxtyping
Requires-Dist: numpy
Requires-Dist: torch
Provides-Extra: dev
Requires-Dist: basedpyright; extra == "dev"
Requires-Dist: pytest; extra == "dev"
Requires-Dist: pytest-lazy-fixtures; extra == "dev"
Requires-Dist: ruff; extra == "dev"
Dynamic: license-file
